[{"CMANAME":"Campbell River","PRUID":59.0,"date":"2022-11-18","days_since_record":1,"Temp":-8.2,"Rank":1,"First Year":1919},{"CMANAME":"Nanaimo","PRUID":59.0,"date":"2022-11-18","days_since_record":1,"Temp":-5.7,"Rank":1,"First Year":1892},{"CMANAME":"Saskatoon","PRUID":47.0,"date":"2022-11-10","days_since_record":9,"Temp":-29.1,"Rank":3,"First Year":1892},{"CMANAME":"Squamish","PRUID":59.0,"date":"2022-11-10","days_since_record":9,"Temp":-4.5,"Rank":3,"First Year":1959},{"CMANAME":"Vernon","PRUID":59.0,"date":"2022-11-09","days_since_record":10,"Temp":-15.0,"Rank":5,"First Year":1893},{"CMANAME":"Medicine Hat","PRUID":48.0,"date":"2022-11-09","days_since_record":10,"Temp":-30.6,"Rank":5,"First Year":1883},{"CMANAME":"Calgary","PRUID":48.0,"date":"2022-11-09","days_since_record":10,"Temp":-30.4,"Rank":5,"First Year":1881},{"CMANAME":"Powell River","PRUID":59.0,"date":"2022-11-09","days_since_record":10,"Temp":-5.2,"Rank":5,"First Year":1924},{"CMANAME":"Lethbridge","PRUID":48.0,"date":"2022-11-09","days_since_record":10,"Temp":-31.3,"Rank":5,"First Year":1886},{"CMANAME":"Port Alberni","PRUID":59.0,"date":"2022-11-09","days_since_record":10,"Temp":-6.2,"Rank":5,"First Year":1917},{"CMANAME":"Edmonton","PRUID":48.0,"date":"2022-11-09","days_since_record":10,"Temp":-35.0,"Rank":5,"First Year":1880},{"CMANAME":"Fredericton","PRUID":13.0,"date":"2022-10-12","days_since_record":38,"Temp":-9.0,"Rank":12,"First Year":1871},{"CMANAME":"Edmundston","PRUID":13.0,"date":"2022-10-10","days_since_record":40,"Temp":-5.8,"Rank":13,"First Year":1913},{"CMANAME":"Charlottetown","PRUID":11.0,"date":"2022-10-03","days_since_record":47,"Temp":-1.5,"Rank":14,"First Year":1872},{"CMANAME":"Peterborough","PRUID":35.0,"date":"2022-10-03","days_since_record":47,"Temp":-4.8,"Rank":14,"First Year":1866},{"CMANAME":"Trois-Rivi\u00e8res","PRUID":24.0,"date":"2022-10-03","days_since_record":47,"Temp":-3.3,"Rank":14,"First Year":1920},{"CMANAME":"Williams Lake","PRUID":59.0,"date":"2022-09-18","days_since_record":62,"Temp":-7.0,"Rank":17,"First Year":1879},{"CMANAME":"Saint John","PRUID":13.0,"date":"2022-07-10","days_since_record":132,"Temp":4.2,"Rank":18,"First Year":1871},{"CMANAME":"Sept-\u00celes","PRUID":24.0,"date":"2022-06-21","days_since_record":151,"Temp":-0.5,"Rank":19,"First Year":1903},{"CMANAME":"Sarnia","PRUID":35.0,"date":"2022-06-19","days_since_record":153,"Temp":6.1,"Rank":20,"First Year":1882},{"CMANAME":"Sault Ste. Marie","PRUID":35.0,"date":"2022-06-04","days_since_record":168,"Temp":-1.5,"Rank":21,"First Year":1945},{"CMANAME":"Quesnel","PRUID":59.0,"date":"2022-05-21","days_since_record":182,"Temp":-9.5,"Rank":22,"First Year":1888},{"CMANAME":"North Battleford","PRUID":47.0,"date":"2022-05-21","days_since_record":182,"Temp":-4.2,"Rank":22,"First Year":1879},{"CMANAME":"Cape Breton","PRUID":12.0,"date":"2022-05-08","days_since_record":195,"Temp":-5.7,"Rank":24,"First Year":1941},{"CMANAME":"Windsor","PRUID":35.0,"date":"2022-04-28","days_since_record":205,"Temp":-5.7,"Rank":25,"First Year":1866},{"CMANAME":"Chatham-Kent","PRUID":35.0,"date":"2022-04-28","days_since_record":205,"Temp":-5.9,"Rank":25,"First Year":1879},{"CMANAME":"Brandon","PRUID":46.0,"date":"2022-04-18","days_since_record":215,"Temp":-17.2,"Rank":27,"First Year":1885},{"CMANAME":"Nelson","PRUID":59.0,"date":"2022-04-16","days_since_record":217,"Temp":-5.0,"Rank":28,"First Year":1904},{"CMANAME":"Prince Rupert","PRUID":59.0,"date":"2022-04-16","days_since_record":217,"Temp":-2.4,"Rank":28,"First Year":1959},{"CMANAME":"Cranbrook","PRUID":59.0,"date":"2022-04-14","days_since_record":219,"Temp":-12.7,"Rank":30,"First Year":1901},{"CMANAME":"Terrace","PRUID":59.0,"date":"2022-04-13","days_since_record":220,"Temp":-5.6,"Rank":31,"First Year":1912},{"CMANAME":"St. Catharines - Niagara","PRUID":35.0,"date":"2022-03-31","days_since_record":233,"Temp":-17.0,"Rank":32,"First Year":1872},{"CMANAME":"Parksville","PRUID":59.0,"date":"2022-02-23","days_since_record":269,"Temp":-8.0,"Rank":33,"First Year":1892},{"CMANAME":"Duncan","PRUID":59.0,"date":"2022-02-23","days_since_record":269,"Temp":-7.7,"Rank":33,"First Year":1921},{"CMANAME":"Moose Jaw","PRUID":47.0,"date":"2022-02-22","days_since_record":270,"Temp":-33.0,"Rank":35,"First Year":1884},{"CMANAME":"Kitchener - Cambridge - Waterloo","PRUID":35.0,"date":"2022-01-29","days_since_record":294,"Temp":-29.2,"Rank":36,"First Year":1879},{"CMANAME":"Guelph","PRUID":35.0,"date":"2022-01-29","days_since_record":294,"Temp":-30.6,"Rank":36,"First Year":1881},{"CMANAME":"Baie-Comeau","PRUID":24.0,"date":"2022-01-27","days_since_record":296,"Temp":-37.4,"Rank":38,"First Year":1947},{"CMANAME":"Ottawa - Gatineau (Ontario part \/ partie de l'Ontario)","PRUID":35.0,"date":"2022-01-22","days_since_record":301,"Temp":-35.1,"Rank":39,"First Year":1870},{"CMANAME":"Toronto","PRUID":35.0,"date":"2022-01-21","days_since_record":302,"Temp":-32.5,"Rank":40,"First Year":1840},{"CMANAME":"Timmins","PRUID":35.0,"date":"2022-01-15","days_since_record":308,"Temp":-41.8,"Rank":41,"First Year":1913},{"CMANAME":"Victoria","PRUID":59.0,"date":"2022-01-01","days_since_record":322,"Temp":-12.4,"Rank":42,"First Year":1872},{"CMANAME":"Vancouver","PRUID":59.0,"date":"2021-12-31","days_since_record":323,"Temp":-45.0,"Rank":43,"First Year":1874},{"CMANAME":"Swift Current","PRUID":47.0,"date":"2021-12-28","days_since_record":326,"Temp":-39.1,"Rank":44,"First Year":1885},{"CMANAME":"Penticton","PRUID":59.0,"date":"2021-12-27","days_since_record":327,"Temp":-22.4,"Rank":45,"First Year":1907},{"CMANAME":"Chilliwack","PRUID":59.0,"date":"2021-12-27","days_since_record":327,"Temp":-38.0,"Rank":45,"First Year":1879},{"CMANAME":"Centre Wellington","PRUID":35.0,"date":"2021-11-27","days_since_record":357,"Temp":-24.0,"Rank":47,"First Year":1882},{"CMANAME":"Brantford","PRUID":35.0,"date":"2021-08-15","days_since_record":461,"Temp":7.7,"Rank":48,"First Year":1876},{"CMANAME":"Saguenay","PRUID":24.0,"date":"2021-07-08","days_since_record":499,"Temp":2.2,"Rank":49,"First Year":1871},{"CMANAME":"Truro","PRUID":12.0,"date":"2021-06-11","days_since_record":526,"Temp":-2.6,"Rank":50,"First Year":1872},{"CMANAME":"Thetford Mines","PRUID":24.0,"date":"2021-05-29","days_since_record":539,"Temp":-1.6,"Rank":51,"First Year":1922},{"CMANAME":"Qu\u00e9bec","PRUID":24.0,"date":"2021-05-29","days_since_record":539,"Temp":-2.6,"Rank":51,"First Year":1872},{"CMANAME":"Essa","PRUID":35.0,"date":"2021-05-29","days_since_record":539,"Temp":-1.1,"Rank":51,"First Year":1926},{"CMANAME":"Cornwall","PRUID":35.0,"date":"2021-05-28","days_since_record":540,"Temp":1.0,"Rank":54,"First Year":1867},{"CMANAME":"Yorkton","PRUID":47.0,"date":"2021-05-07","days_since_record":561,"Temp":-8.3,"Rank":55,"First Year":1884},{"CMANAME":"Greater Sudbury \/ Grand Sudbury","PRUID":35.0,"date":"2021-04-26","days_since_record":572,"Temp":-8.5,"Rank":56,"First Year":1887},{"CMANAME":"Winnipeg","PRUID":46.0,"date":"2021-04-24","days_since_record":574,"Temp":-11.5,"Rank":57,"First Year":1872},{"CMANAME":"Whitehorse","PRUID":60.0,"date":"2021-04-11","days_since_record":587,"Temp":-34.0,"Rank":58,"First Year":1900},{"CMANAME":"Trail","PRUID":59.0,"date":"2021-04-11","days_since_record":587,"Temp":-4.6,"Rank":58,"First Year":1913},{"CMANAME":"Rouyn-Noranda","PRUID":24.0,"date":"2020-10-31","days_since_record":749,"Temp":-14.9,"Rank":60,"First Year":1927},{"CMANAME":"Kamloops","PRUID":59.0,"date":"2020-10-25","days_since_record":755,"Temp":-14.0,"Rank":61,"First Year":1878},{"CMANAME":"Salmon Arm","PRUID":59.0,"date":"2020-10-25","days_since_record":755,"Temp":-8.5,"Rank":61,"First Year":1893},{"CMANAME":"Montr\u00e9al","PRUID":24.0,"date":"2020-09-22","days_since_record":788,"Temp":-3.4,"Rank":63,"First Year":1871},{"CMANAME":"Owen Sound","PRUID":35.0,"date":"2020-09-18","days_since_record":792,"Temp":0.3,"Rank":64,"First Year":1875},{"CMANAME":"Prince Albert","PRUID":47.0,"date":"2020-09-16","days_since_record":794,"Temp":-7.5,"Rank":65,"First Year":1884},{"CMANAME":"Regina","PRUID":47.0,"date":"2020-09-08","days_since_record":802,"Temp":-4.5,"Rank":66,"First Year":1883},{"CMANAME":"London","PRUID":35.0,"date":"2020-07-26","days_since_record":846,"Temp":4.0,"Rank":67,"First Year":1871},{"CMANAME":"Oshawa","PRUID":35.0,"date":"2020-05-13","days_since_record":920,"Temp":-3.3,"Rank":68,"First Year":1882},{"CMANAME":"Norfolk","PRUID":35.0,"date":"2020-05-13","days_since_record":920,"Temp":-3.8,"Rank":68,"First Year":1866},{"CMANAME":"Ottawa - Gatineau (partie du Qu\u00e9bec \/ Quebec part)","PRUID":24.0,"date":"2020-05-13","days_since_record":920,"Temp":-6.1,"Rank":68,"First Year":1911},{"CMANAME":"Thunder Bay","PRUID":35.0,"date":"2020-05-11","days_since_record":922,"Temp":-8.4,"Rank":71,"First Year":1877},{"CMANAME":"Halifax","PRUID":12.0,"date":"2020-05-10","days_since_record":923,"Temp":-6.5,"Rank":72,"First Year":1871},{"CMANAME":"Kingston","PRUID":35.0,"date":"2020-05-09","days_since_record":924,"Temp":-4.1,"Rank":73,"First Year":1872},{"CMANAME":"Hamilton","PRUID":35.0,"date":"2020-05-09","days_since_record":924,"Temp":-3.8,"Rank":73,"First Year":1866},{"CMANAME":"Barrie","PRUID":35.0,"date":"2020-04-27","days_since_record":936,"Temp":-8.0,"Rank":75,"First Year":1866},{"CMANAME":"North Bay","PRUID":35.0,"date":"2020-04-23","days_since_record":940,"Temp":-12.4,"Rank":76,"First Year":1887},{"CMANAME":"Dawson Creek","PRUID":59.0,"date":"2020-04-03","days_since_record":960,"Temp":-30.2,"Rank":77,"First Year":1926},{"CMANAME":"Abbotsford - Mission","PRUID":59.0,"date":"2020-03-16","days_since_record":978,"Temp":-5.5,"Rank":78,"First Year":1909},{"CMANAME":"Sherbrooke","PRUID":24.0,"date":"2019-11-17","days_since_record":1098,"Temp":-21.6,"Rank":79,"First Year":1888},{"CMANAME":"Belleville - Quinte West","PRUID":35.0,"date":"2019-11-13","days_since_record":1102,"Temp":-18.8,"Rank":80,"First Year":1895},{"CMANAME":"St. John's","PRUID":10.0,"date":"2019-01-04","days_since_record":1415,"Temp":-19.4,"Rank":81,"First Year":1874},{"CMANAME":"Miramichi","PRUID":13.0,"date":"2018-11-19","days_since_record":1461,"Temp":-20.2,"Rank":82,"First Year":1873},{"CMANAME":"Bathurst","PRUID":13.0,"date":"2018-11-19","days_since_record":1461,"Temp":-22.5,"Rank":82,"First Year":1872},{"CMANAME":"Wood Buffalo","PRUID":48.0,"date":"2018-10-08","days_since_record":1503,"Temp":-16.3,"Rank":84,"First Year":1883},{"CMANAME":"Prince George","PRUID":59.0,"date":"2018-10-03","days_since_record":1508,"Temp":-12.8,"Rank":85,"First Year":1912},{"CMANAME":"Fort St. John","PRUID":59.0,"date":"2018-10-01","days_since_record":1510,"Temp":-8.2,"Rank":86,"First Year":1910},{"CMANAME":"Moncton","PRUID":13.0,"date":"2018-06-04","days_since_record":1629,"Temp":-3.2,"Rank":87,"First Year":1871},{"CMANAME":"Kentville","PRUID":12.0,"date":"2018-06-04","days_since_record":1629,"Temp":-1.9,"Rank":87,"First Year":1912},{"CMANAME":"Gander","PRUID":10.0,"date":"2017-04-19","days_since_record":2040,"Temp":-10.1,"Rank":89,"First Year":1937},{"CMANAME":"Courtenay","PRUID":59.0,"date":"2014-07-11","days_since_record":3053,"Temp":3.0,"Rank":90,"First Year":1893},{"CMANAME":"Kelowna","PRUID":59.0,"date":"2009-10-12","days_since_record":4786,"Temp":-10.7,"Rank":91,"First Year":1899},{"CMANAME":"Lloydminster (Saskatchewan part \/ partie de la Saskatchewan)","PRUID":47.0,"date":"2009-03-16","days_since_record":4996,"Temp":-39.0,"Rank":92,"First Year":1904},{"CMANAME":"Kawartha Lakes","PRUID":35.0,"date":"2008-03-10","days_since_record":5367,"Temp":-25.0,"Rank":93,"First Year":1880},{"CMANAME":"New Glasgow","PRUID":12.0,"date":"2003-04-17","days_since_record":7156,"Temp":-11.0,"Rank":94,"First Year":1940}]